[
 {
  "contributed_translation_doctype_name": null,
  "docstatus": 0,
  "doctype": "Translation",
  "language": "es",
  "modified": "2021-04-30 09:12:25.898945",
  "name": "7f55287301",
  "parent": null,
  "parentfield": null,
  "parenttype": null,
  "source_name": "Create Sales Order",
  "status": "Saved",
  "target_name": "Crear orden de venta"
 },
 {
  "contributed_translation_doctype_name": null,
  "docstatus": 0,
  "doctype": "Translation",
  "language": "es",
  "modified": "2021-04-30 09:38:00.155097",
  "name": "2bf178db6a",
  "parent": null,
  "parentfield": null,
  "parenttype": null,
  "source_name": "Add Customer",
  "status": "Saved",
  "target_name": "Agregar Cliente"
 },
 {
  "contributed_translation_doctype_name": null,
  "docstatus": 0,
  "doctype": "Translation",
  "language": "es",
  "modified": "2021-05-10 16:15:13.068556",
  "name": "3497187195",
  "parent": null,
  "parentfield": null,
  "parenttype": null,
  "source_name": "New Sales Invoice",
  "status": "Saved",
  "target_name": "Crear Factura de Venta"
 },
 {
  "contributed_translation_doctype_name": null,
  "docstatus": 0,
  "doctype": "Translation",
  "language": "es",
  "modified": "2021-05-10 16:17:31.378210",
  "name": "17968bcae1",
  "parent": null,
  "parentfield": null,
  "parenttype": null,
  "source_name": "Create",
  "status": "Saved",
  "target_name": "Crear"
 },
 {
  "contributed_translation_doctype_name": null,
  "docstatus": 0,
  "doctype": "Translation",
  "language": "es",
  "modified": "2021-05-10 16:36:18.412538",
  "name": "d3cd4fb007",
  "parent": null,
  "parentfield": null,
  "parenttype": null,
  "source_name": "Item",
  "status": "Saved",
  "target_name": "Producto"
 },
 {
  "contributed_translation_doctype_name": null,
  "docstatus": 0,
  "doctype": "Translation",
  "language": "es",
  "modified": "2021-05-10 19:32:30.144147",
  "name": "ff98067489",
  "parent": null,
  "parentfield": null,
  "parenttype": null,
  "source_name": "Cashier Closing",
  "status": "Saved",
  "target_name": "Cierre de Caja"
 },
 {
  "contributed_translation_doctype_name": null,
  "docstatus": 0,
  "doctype": "Translation",
  "language": "es",
  "modified": "2021-06-05 19:36:13.409634",
  "name": "370c21dab4",
  "parent": null,
  "parentfield": null,
  "parenttype": null,
  "source_name": "Schedule",
  "status": "Saved",
  "target_name": "Horario"
 },
 {
  "contributed_translation_doctype_name": null,
  "docstatus": 0,
  "doctype": "Translation",
  "language": "es",
  "modified": "2021-06-05 19:36:43.224886",
  "name": "b919fa56f3",
  "parent": null,
  "parentfield": null,
  "parenttype": null,
  "source_name": "Add Schedule",
  "status": "Saved",
  "target_name": "Agregar Horario"
 },
 {
  "contributed_translation_doctype_name": null,
  "docstatus": 0,
  "doctype": "Translation",
  "language": "es",
  "modified": "2021-06-05 19:37:01.050586",
  "name": "9d807ef20f",
  "parent": null,
  "parentfield": null,
  "parenttype": null,
  "source_name": "Clear Table",
  "status": "Saved",
  "target_name": "Limpiar Tabla"
 },
 {
  "contributed_translation_doctype_name": null,
  "docstatus": 0,
  "doctype": "Translation",
  "language": "es",
  "modified": "2021-06-05 19:37:34.416248",
  "name": "23ecf385a6",
  "parent": null,
  "parentfield": null,
  "parenttype": null,
  "source_name": "Start Time",
  "status": "Saved",
  "target_name": "Hora de Inicio"
 },
 {
  "contributed_translation_doctype_name": null,
  "docstatus": 0,
  "doctype": "Translation",
  "language": "es",
  "modified": "2021-06-05 19:37:56.549699",
  "name": "0143614f19",
  "parent": null,
  "parentfield": null,
  "parenttype": null,
  "source_name": "End Time",
  "status": "Saved",
  "target_name": "Hora de Salida"
 },
 {
  "contributed_translation_doctype_name": null,
  "docstatus": 0,
  "doctype": "Translation",
  "language": "es",
  "modified": "2021-06-05 19:38:09.028320",
  "name": "36c4710498",
  "parent": null,
  "parentfield": null,
  "parenttype": null,
  "source_name": "Days",
  "status": "Saved",
  "target_name": "Dias"
 },
 {
  "contributed_translation_doctype_name": null,
  "docstatus": 0,
  "doctype": "Translation",
  "language": "es",
  "modified": "2021-06-05 19:38:19.836834",
  "name": "b98fa676dd",
  "parent": null,
  "parentfield": null,
  "parenttype": null,
  "source_name": "Add",
  "status": "Saved",
  "target_name": "Agregar"
 },
 {
  "contributed_translation_doctype_name": null,
  "docstatus": 0,
  "doctype": "Translation",
  "language": "es",
  "modified": "2021-06-05 23:38:06.080824",
  "name": "9caff7a137",
  "parent": null,
  "parentfield": null,
  "parenttype": null,
  "source_name": "The Schedule Table has been cleared",
  "status": "Saved",
  "target_name": "La Tabla de Horarios ha sido limpiada"
 }
]